toPrint/__init__.py
toPrint/_version.py
toPrint/toPrint.py
toprint-0.1.32.dist-info/licenses/AUTHORS.txt
toprint-0.1.32.dist-info/licenses/LICENSE
toprint-0.1.32.dist-info/METADATA
toprint-0.1.32.dist-info/WHEEL
toprint-0.1.32.dist-info/entry_points.txt
toprint-0.1.32.dist-info/top_level.txt
toprint-0.1.32.dist-info/RECORD
