Metadata-Version: 2.4
Name: toprint
Version: 0.1.32
Summary: 2print/toprint: Python library for printing and converting between HTML, PDF, ZPL, and image formats with printer support. Also known as 2print or to-print.
Home-page: https://github.com/text2doc/toPrint
Author: Tom Softreck
Author-email: info@softreck.dev
Project-URL: Bug Reports, https://github.com/text2doc/toPrint/issues
Project-URL: Source, https://github.com/text2doc/toPrint
Project-URL: Documentation, https://github.com/text2doc/toPrint#readme
Project-URL: Changelog, https://github.com/text2doc/toPrint/releases
Keywords: printing,pdf,html,zpl,label,printer,conversion,2print,2-print,print2,print-2,toprint,to-print,html2print,html-to-print,html2pdf,html-to-pdf,html2zpl,html-to-zpl,html2img,html-to-image,html2doc,html-to-doc,html2docx,html-to-docx,html2md,html-to-md,html2markdown,html-to-markdown,html2xml,html-to-xml,html2json,html-to-json,pdf2print,pdf-to-print,pdf2html,pdf-to-html,pdf2zpl,pdf-to-zpl,pdf2img,pdf-to-image,pdf2doc,pdf-to-doc,pdf2docx,pdf-to-docx,pdf2md,pdf-to-md,pdf2markdown,pdf-to-markdow
Classifier: Development Status :: 4 - Beta
Classifier: Intended Audience :: Developers
Classifier: Intended Audience :: Manufacturing
Classifier: Intended Audience :: System Administrators
Classifier: Topic :: Software Development :: Libraries :: Python Modules
Classifier: Topic :: Printing
Classifier: Topic :: Text Processing :: Markup :: HTML
Classifier: Topic :: Multimedia :: Graphics :: Graphics Conversion
Classifier: Topic :: Office/Business :: Office Suites
Classifier: License :: OSI Approved :: Apache Software License
Classifier: Programming Language :: Python :: 3
Classifier: Programming Language :: Python :: 3.7
Classifier: Programming Language :: Python :: 3.8
Classifier: Programming Language :: Python :: 3.9
Classifier: Programming Language :: Python :: 3.10
Classifier: Programming Language :: Python :: 3.11
Classifier: Programming Language :: Python :: 3.12
Classifier: Operating System :: OS Independent
Requires-Python: >=3.7
License-File: LICENSE
License-File: AUTHORS.txt
Requires-Dist: weasyprint>=53.0
Requires-Dist: Pillow>=8.0.0
Requires-Dist: reportlab>=3.6.0
Dynamic: author
Dynamic: author-email
Dynamic: classifier
Dynamic: description
Dynamic: description-content-type
Dynamic: home-page
Dynamic: keywords
Dynamic: license-file
Dynamic: project-url
Dynamic: requires-dist
Dynamic: requires-python
Dynamic: summary
